py_serializer/constants.py
py_serializer/json_serializer.py
py_serializer/serializer.py
py_serializer/xml_serializer.py
py_serializer_100523-0.1.2.dist-info/METADATA
py_serializer_100523-0.1.2.dist-info/WHEEL
py_serializer_100523-0.1.2.dist-info/top_level.txt
py_serializer_100523-0.1.2.dist-info/RECORD
