Metadata-Version: 2.1
Name: py-serializer-100523
Version: 0.1.2
Summary: Demo library
Home-page: https://py-serializer.readthedocs.io/
Author: Alina Bybko
Author-email: alina_bybko@email.com
License: MIT
Platform: UNKNOWN
Classifier: Intended Audience :: Developers
Classifier: License :: OSI Approved :: MIT License
Classifier: Programming Language :: Python
Classifier: Programming Language :: Python :: 3
Classifier: Programming Language :: Python :: 3.6
Classifier: Programming Language :: Python :: 3.7
Classifier: Programming Language :: Python :: 3.8
Classifier: Programming Language :: Python :: 3.9
Classifier: Operating System :: OS Independent
Requires-Dist: regex
